{
  "skins":{
    "AboriginalSivir":"huntress",
    "AbyssChogath":"loch_ness",
    "AhriFireFox":"foxfire",
    "AhriHanbok":"dynasty",
    "AhriShadowfox":"midnight",
    "AnnieFrankenstein":"frankentibbers",
    "AnnieFrostFire":"frostfire",
    "ArmoredAlistar":"infernal",
    "ArmoredSion":"warmonger",
    "AssassinOriana":"bladecraft",
    "AsylumJester":"asylum",
    "BadrobotAmumu":"sad_robot",
    "BakerMorgana":"sinful_succulence",
    "BaseballTrundle":"lil_slugger",
    "BattleCryophoenix":"noxus_hunter",
    "BattlebunnyRiven":"battle_bunny",
    "BirdCryophoenix":"bird_of_prey",
    "BlackMinotaur":"black",
    "BladesMorgana":"blade_mistress",
    "BloodkingVladimir":"blood_lord",
    "BlueAlistar":"unchained",
    "BlueKennen":"swamp_master",
    "BobsledCorki":"ice_toboggan",
    "BoxerSteamgolem":"boom_boom",
    "BreakoutGraves":"jailbreak",
    "BurntMaokai":"charred",
    "ButterflyKogMaw":null,
    "CandyCaneFiddlesticks":"dark_candy",
    "CandyCaneMissFortune":null,
    "ChristmasMaokai":"festive",
    "ClassicBlindMonk":"traditional",
    "ClassyGragas":"esq",
    "CleopatraNidalee":"pharaoh",
    "ClericSoraka":"celestine",
    "ClockworkJester":"workshop",
    "CommandoXenZhao":"commando",
    "CopCaitlyn":"officer",
    "CorporateMundo":"corporate",
    "CouncilMasterYi":"chosen",
    "CowboyMinotaur":"longhorn",
    "CowboyTwistedFate":"high_noon",
    "CrystalBowmaster":"amethyst",
    "CyberBladeIrelia":"infiltrator",
    "CyberEzreal":"pulsefire",
    "CyberNocturne":"eternum",
    "DacianKnightPantheon":"glaive_warrior",
    "DandyChogath":"gentleman",
    "DapperVeigar":"superb_villain",
    "Darius_Emperor":"lord",
    "Darius_ZaunKnight":"bioforge",
    "DarkBladeKassadin":"harbinger",
    "DarkMetalRammus":"chrome",
    "DarkvoidMalzahar":"overlord",
    "DeepseaKogMaw":"deep_sea",
    "DesertKatarina":"sandstorm",
    "DestroyerMordekaiser":"lord",
    "DinosaurChogath":"jurassic",
    "DrKennen":"md",
    "DragonBlindMonk":"dragon_fist",
    "DragoonJarvanIV":"darkforge",
    "Draven_SoulReaper":"soul_reaver",
    "DreadKnightNasus":"dreadknight",
    "DreadknightTaric":"bloodstone",
    "EasterbunnyTeemo":"cottontail",
    "EliseLotusFlower":"death_blossom",
    "EmeraldGemknight":"emerald",
    "EmoAmumu":"emumu",
    "ExecutionerMundo":"executioner",
    "ExperimentChemicalman":"augmented",
    "FailedHeimerdinger":"blast_zone",
    "FallenMorgana":"exiled",
    "FioraArmored":"nightraven",
    "FioraMusketeer":"royal_guard",
    "FioraSchoolTeacher":"headmistress",
    "FireMonkeyKing":"volcanic",
    "FirewolfWarwick":"firefang",
    "FireworksCorki":"dragonwing",
    "FizzArctic":"tundra",
    "FossilKogMaw":"jurassic",
    "FreljordBowmaster":"freljord",
    "FreljordSivir":"bandit",
    "FrostBladeIrelia":"frostblade",
    "FrostFireBrand":"cryocore",
    "FrostNocturne":"frozen_terror",
    "FrostqueenJanna":"frost_queen",
    "FrozenRammus":"freljord",
    "GasmaskBrand":"apocalyptic",
    "GeishaKarma":"sakura",
    "GenieMalzahar":"djinn",
    "GhostFiddlesticks":"spectral",
    "GhostGangplank":"spooky",
    "GhostNocturne":"haunting",
    "GladiatorXenZhao":"viscero",
    "Gladiator_Jax":"jaximus",
    "GoldenMinotaur":"golden",
    "GothOriana":"gothic",
    "GrandAdmiralSwain":"tyrant",
    "GraveDiggerMaokai":"haunted",
    "GreekCassiopeia":"mythic",
    "GrimLich":"grim_reaper",
    "GunMetalJudicator":"battleborn",
    "HatterJester":"mad_hatter",
    "HextechChemicalMan":"hextech",
    "HillBillyGragas":"hillbilly",
    "HumanSoraka":"divine",
    "Immortal_Jax":"nemesis",
    "ImperialXenZhao":"imperial",
    "IncognitoBlitz":"definitely_not",
    "IonianMasterYi":"ionia",
    "IronForgeXerath":"scorched_earth",
    "IronMaskTwitch":"medieval",
    "IronXerath":"battlecast",
    "JackOfHeartsCardmaster":"jackof_hearts",
    "Jayce_Gentleman":"debonair",
    "Jayce_Sentinel":"full_metal",
    "JudgementJudicator":"judgment",
    "KaiserTwitch":"whistler_village",
    "KatarinaReferee":"red_card",
    "KhazixDroid":"mecha",
    "KnightShyvana":"ironscale",
    "KoreanShaco":"masked",
    "Leona-IronSolari":"iron_solari",
    "Leona-battleworn":"defender",
    "Leona-phoenix":"valkyrie",
    "LightningJanna":"tempest",
    "LordMonkeyKing":"general",
    "LubuJarvanIV":"warring_kingdoms",
    "LunarRevelCassiopeia":"jade_fang",
    "MadScientistChemicalman":"mad_scientist",
    "MagicianLeblanc":"prestigious",
    "MassacreNocturne":"ravager",
    "MatadorMinotaur":"matador",
    "MechanicHeimerdinger":"piltover_customs",
    "MedievalHecarim":"blood_knight",
    "MercenaryGraves":"hired_gun",
    "MetalMordekaiser":"pentakill",
    "MetalSion":"hextech",
    "MetalSona":"pentakill",
    "MetalWingedJudicator":"aether_wing",
    "MilitaryCaitlyn":"resistance",
    "MinutemanPirate":"minuteman",
    "MonsterHunterJarvanIV":"dragon_slayer",
    "MuayThaiBlindMonk":"muay_thai",
    "MundoMundo":"mundo",
    "NautilusAstronaut":"astronautilus",
    "NautilusSubmarine":"abyssal",
    "NewYearDragonKogMaw":null,
    "NiflheimOlaf":"glacial",
    "NorthernCaitlyn":"arctic_warfare",
    "NoxusKatarina":"high_command",
    "NunuBattle":"demolisher",
    "NutcrackerJester":"nutcracko",
    "OldStZilean":"old_saint",
    "OlympicAmumu":"vancouver",
    "OniAkali":"blood_moon",
    "OniShen":"blood_moon",
    "OrcMundo":"rageborn",
    "PAXCardmaster":"pax",
    "PaxSona":"arcade",
    "PhantomLich":"phantom",
    "PiltoverCustomsBlitz":"piltover_customs",
    "PinkGemknight":"pink",
    "PinkTristana":"riot_girl",
    "PirateFiddlesticks":null,
    "PirateKatarina":"bilgewater",
    "PoisonFrogKogMaw":"sonoran",
    "PreVoidKassadin":null,
    "PumpkinHeadFiddlesticks":"pumpkinhead",
    "PunkTwitch":"vandal",
    "QueenBowmaster":"queen",
    "RagdollOriana":"sewn_chaos",
    "RaggedyPoppy":"ragdoll",
    "RangerGaren":"rugged",
    "RattlesnakeCassiopeia":"desperada",
    "RedKennen":"deadly",
    "RedSivir":"spectacular",
    "RedVeigar":"white_mage",
    "RegalknightPoppy":"battle_regalia",
    "RegiftAmumu":"re_gifted",
    "Renekton_brutal":"bloodfury",
    "RiotChemicalMan":"riot_squad",
    "RoboRammus":"full_metal",
    "RockmonsterMalphite":"marble",
    "RomaKassadin":"festival",
    "RustySteamgolem":"rusty",
    "SamuraiShen":"warlord",
    "SavageWolfman":"feral",
    "ScholarRyze":"professor",
    "ScurvyDogTristana":"buccaneer",
    "SeasnakeCassiopeia":"siren",
    "Season2Riven":"championship",
    "SecretAgentMissFortune":null,
    "SejuaniBeastLoad":"sabretusk",
    "SejuaniDeathKnight":"darkrider",
    "ShadowShyvana":"darkflame",
    "Shaolin_Jax":"temple",
    "SherwoodBowmaster":"sherwood_forest",
    "SilverJudicator":"silver",
    "SilverNasus":"galactic",
    "SkarnerRunes":"earthrune",
    "SkarnerScorpion":"sandscourge",
    "SnowmanHeimerdinger":"snowmerdinger",
    "SoccerAkali":"all_star",
    "SoccerEzreal":"striker",
    "SoccerSteamgolem":"goalkeeper",
    "StatueLich":"statue",
    "SteellegionGaren":"steel_legion",
    "SungoddessKarma":"sun_goddess",
    "SurferChemicalMan":"surfer",
    "TalonNemesis":"crimson_elite",
    "TalonSilverdragon":"dragonblade",
    "TalonStreet":"renegade",
    "TangoCardmaster":"tango",
    "TempleBlindMonk":"acolyte",
    "ThreshUndersea":"deep_terror",
    "TimemachineZilean":"time_machine",
    "TribalMasterYi":"headhunter",
    "TryndamereDemonsword":"demonblade",
    "TundraWolfman":"tundra_hunter",
    "USACryophoenix":"team_spirit",
    "UnmaskedJudicator":"unmasked",
    "UrfRiderCorki":"urfrider",
    "ValhallanOlaf":"forsaken",
    "VandalsBrand":"vandal",
    "VandalsGragas":"vandal",
    "VandalsVladimir":"vandal",
    "VarusAscended":"arclight",
    "VarusDarkCrystal":"blight_crystal",
    "VayneModern":"vindicator",
    "VayneValentine":"heartseeker",
    "VayneVictorian":"aristocrat",
    "ViRacer":"neon_strike",
    "Viktor_fullmachine":"full_machine",
    "ViridianJudicator":"viridian",
    "VoidCrystalRyze":"dark_crystal",
    "VolibearArctic":"northern_storm",
    "VolibearKing":"thunder_lord",
    "Warhero":"victorious",
    "WarheroJarvanIV":"victorious",
    "WastelandMissFortune":"road_warrior",
    "WhiteHairLeblanc":"wicked",
    "WingedHussarXenZhao":"winged_hussar",
    "WinnerRyze":"triumphant",
    "WinterbellLeblanc":"mistletoe",
    "WitchLux":"sorceress",
    "WoadBowmaster":"woad",
    "WraithHecarim":"reaper",
    "XmasKatarina":"slay_belle",
    "YellowAkali":"stinger",
    "YellowJester":"royal",
    "YellowjacketShen":"yellow_jacket",
    "ZedStormNinja":"shockblade",
    "ZhaoYunXinZhao":"warring_kingdoms",
    "ZiggsGeneral":"major",
    "ZiggsSnowday":"snow_day",
    "Zyra_hellvine":"wildfire",
    "luluClassic":"wicked",
    "luluDarkCandy":"bittersweet",
    "mercenaryAkali":"silverfang",
    "pentakillLich":"pentakill",
    "redknightPoppy":"scarlet_hammer"
  }
}